fulltrader/__init__.py
fulltrader/__main__.py
fulltrader/cli.py
fulltrader/core/__init__.py
fulltrader/core/shared/__init__.py
fulltrader/infra/__init__.py
fulltrader/use_cases/__init__.py
fulltrader/use_cases/hello/__init__.py
fulltrader/use_cases/hello/say_hello.py
fulltrader-0.1.2.dist-info/METADATA
fulltrader-0.1.2.dist-info/WHEEL
fulltrader-0.1.2.dist-info/entry_points.txt
fulltrader-0.1.2.dist-info/licenses/LICENSE
fulltrader-0.1.2.dist-info/RECORD
