Metadata-Version: 2.4
Name: fulltrader
Version: 0.1.2
Summary: Pacote FullTrader
Project-URL: Homepage, https://example.com/fulltrader
Project-URL: Source, https://example.com/fulltrader/repo
Author-email: FullTrader <data-teams@fulltrader.com>
License: MIT License
License-File: LICENSE
Keywords: api,dados,data,fulltrader
Classifier: License :: OSI Approved :: MIT License
Classifier: Operating System :: OS Independent
Classifier: Programming Language :: Python :: 3
Classifier: Programming Language :: Python :: 3 :: Only
Classifier: Programming Language :: Python :: 3.9
Classifier: Programming Language :: Python :: 3.10
Classifier: Programming Language :: Python :: 3.11
Classifier: Programming Language :: Python :: 3.12
Requires-Python: >=3.9
Provides-Extra: dev
Requires-Dist: build>=1.2.1; extra == 'dev'
Requires-Dist: mypy>=1.10.0; extra == 'dev'
Requires-Dist: pytest>=7; extra == 'dev'
Requires-Dist: ruff>=0.5.0; extra == 'dev'
Requires-Dist: twine>=5.1.1; extra == 'dev'
